{
  "fields": [
        {
      "name": "metadata_id",
      "title": "Metadata ID",
      "type": "string",
      "raises": "error",
      "constraints": {
        "required": true
      }
    },
    {
      "name": "program_id",
      "title": "Program ID",
      "type": "string",
      "raises": "error",
      "constraints": {
        "required": true
      }
    },
    {
      "name": "contact_id",
      "title": "Contact ID",
      "type": "string",
      "raises": "error",
      "constraints": {
        "required": true
      }
    },
    {
      "name": "title",
      "title": "Title",
      "type": "string",
      "raises": "error",
      "constraints": {
        "required": true
      }
    },
    {
      "name": "description",
      "title": "Description",
      "type": "string",
      "raises": "error",
      "constraints": {
        "required": true
      }
    },
    {
      "name": "bounding_box",
      "title": "Bounding Box",
      "type": "geojson"
    },
    {
      "name": "start_date",
      "title": "Start Date",
      "type": "date"
    },
    {
      "name": "end_date",
      "title": "End Date",
      "type": "date"
    }
  ]
}